gecrypt
