Metadata-Version: 2.1
Name: git-easy-crypt
Version: 1.0.4
Summary: The easy way to encrypt/decrypt private files in the git repo.
Home-page: https://github.com/taojy123/git-easy-crypt
Author: tao.py
Author-email: taojy123@163.com
License: MIT
Keywords: git encrypt decrypt
Platform: UNKNOWN
Classifier: License :: OSI Approved :: MIT License
Classifier: Programming Language :: Python :: 2
Classifier: Programming Language :: Python :: 2.7
Classifier: Programming Language :: Python :: 3
Classifier: Programming Language :: Python :: 3.7
Classifier: Topic :: Software Development :: Version Control :: Git
